pytwoway/__init__.py
pytwoway/attrition.py
pytwoway/blm.py
pytwoway/blm_dynamic.py
pytwoway/blm_interacted.py
pytwoway/borovickovashimer.py
pytwoway/command_line.py
pytwoway/cre.py
pytwoway/fe.py
pytwoway/fecontrol.py
pytwoway/montecarlo.py
pytwoway/simblm.py
pytwoway/simbs.py
pytwoway/simdblm.py
pytwoway/sorkin.py
pytwoway/util.py
pytwoway/Q/Q.py
pytwoway/Q/__init__.py
pytwoway/attrition_utils/__init__.py
pytwoway/attrition_utils/attrition_utils.py
pytwoway/constraints/__init__.py
pytwoway/constraints/constraints.py
pytwoway/diagnostics/__init__.py
pytwoway/diagnostics/plot_extendedeventstudy.py
pytwoway/preconditioners/__init__.py
pytwoway/preconditioners/ichol.py
pytwoway/preconditioners/jacobi.py
pytwoway/preconditioners/vcycle.py
pytwoway-0.3.21.dist-info/LICENSE
pytwoway-0.3.21.dist-info/METADATA
pytwoway-0.3.21.dist-info/WHEEL
pytwoway-0.3.21.dist-info/entry_points.txt
pytwoway-0.3.21.dist-info/top_level.txt
pytwoway-0.3.21.dist-info/RECORD
