Metadata-Version: 2.1
Name: pytwoway
Version: 0.3.21
Summary: Estimate two way fixed effect labor models
Home-page: https://github.com/tlamadon/pytwoway
Author: Thibaut Lamadon
Author-email: thibaut.lamadon@gmail.com
Classifier: Programming Language :: Python :: 3
Classifier: License :: OSI Approved :: MIT License
Classifier: Operating System :: OS Independent
Requires-Python: >=3.6
License-File: LICENSE
Requires-Dist: numpy
Requires-Dist: pandas
Requires-Dist: numba
Requires-Dist: paramsdict (>=0.0.3)
Requires-Dist: bipartitepandas (>=1.1.3)
Requires-Dist: scipy
Requires-Dist: statsmodels
Requires-Dist: pyamg
Requires-Dist: qpsolvers
Requires-Dist: quadprog
Requires-Dist: ConfigArgParse
Requires-Dist: matplotlib
Requires-Dist: tqdm
